redis_schematics/__init__.py
redis_schematics/exceptions.py
redis_schematics/patches.py
redis_schematics/utils.py
tests/__init__.py
tests/test_integration.py
redis_schematics-0.3.1.dist-info/METADATA
redis_schematics-0.3.1.dist-info/WHEEL
redis_schematics-0.3.1.dist-info/top_level.txt
redis_schematics-0.3.1.dist-info/RECORD
