Metadata-Version: 2.1
Name: redis-schematics
Version: 0.3.1
Summary: Redis storage backend for schematics.
Home-page: https://github.com/loggi/redis-schematics
Author: Gabriela Surita
Author-email: gsurita@loggi.com
License: Apache License (2.0)
Keywords: loggi,schematics,redis
Platform: UNKNOWN
Classifier: Intended Audience :: Developers
Classifier: Operating System :: OS Independent
Classifier: Programming Language :: Python
Classifier: Programming Language :: Python :: 3
Classifier: Programming Language :: Python :: 3.4
Classifier: Programming Language :: Python :: 3.5
Classifier: Programming Language :: Python :: 3.6
Classifier: Programming Language :: Python :: 3.7
Requires-Dist: schematics
Requires-Dist: redis
